{
    "string":[
        {
            "name":"ohos_bgmode_prompt_audio_recording",
            "value":"En optagelsesopgave er i gang.",
            "attr":{
                "priority":"translate"
            }
        },
        {
            "name":"ohos_bgmode_prompt_audio_playback",
            "value":"En lydafspilningsopgave er i gang.",
            "attr":{
                "priority":"translate"
            }
        },
        {
            "name":"ohos_bgmode_prompt_multidevice_connection",
            "value":"En distribueret opgave er i gang.",
            "attr":{
                "priority":"translate"
            }
        },
        {
            "name":"ohos_bgmode_prompt_voip",
            "value":"En opkaldsrelateret opgave er i gang.",
            "attr":{
                "priority":"translate"
            }
        },
        {
            "name":"ohos_bgmode_prompt_location",
            "value":"En positionerings\u200bopgave er i gang.",
            "attr":{
                "priority":"LT"
            }
        },
        {
            "name":"ohos_bgmode_prompt_wifi_interaction",
            "value":"En WLAN-relateret opgave er i gang.",
            "attr":{
                "priority":"translate"
            }
        },
        {
            "name":"ohos_bgmode_prompt_bluetooth_interaction",
            "value":"En Bluetooth-relateret opgave er i gang.",
            "attr":{
                "priority":"translate"
            }
        },
        {
            "name":"ohos_bgmode_prompt_task_keeping",
            "value":"En beregningsopgave er i gang.",
            "attr":{
                "priority":"translate"
            }
        },
        {
            "name":"ohos_bgmode_prompt_data_transfer",
            "value":"En dataoverførsels\u200bopgave er i gang.",
            "attr":{
                "priority":"LT"
            }
        },
        {
            "name":"ohos_bgsubmode_prompt_car_key",
            "value":"Fjernbetjeningsbil\u200bnøgle deaktiveres, hvis du lukker dette kort.",
            "attr":{
                "priority":"LT"
            }
        }
    ]
}